mt/net/__init__.py
mt/net/base.py
mt/net/host_port.py
mt/net/port_forwarding.py
mt/net/port_forwarding_async.py
mt/net/ssh_forwarding.py
mt/net/version.py
mtnet-0.3.2.dist-info/licenses/LICENSE
mtnet-0.3.2.dist-info/METADATA
mtnet-0.3.2.dist-info/WHEEL
mtnet-0.3.2.dist-info/top_level.txt
mtnet-0.3.2.dist-info/RECORD
